dex_retargeting/__init__.py
dex_retargeting/constants.py
dex_retargeting/kinematics_adaptor.py
dex_retargeting/optimizer.py
dex_retargeting/optimizer_utils.py
dex_retargeting/retargeting_config.py
dex_retargeting/robot_wrapper.py
dex_retargeting/seq_retarget.py
dex_retargeting/yourdfpy.py
dex_retargeting/configs/offline/ability_hand_left.yml
dex_retargeting/configs/offline/ability_hand_right.yml
dex_retargeting/configs/offline/allegro_hand_left.yml
dex_retargeting/configs/offline/allegro_hand_right.yml
dex_retargeting/configs/offline/inspire_hand_left.yml
dex_retargeting/configs/offline/inspire_hand_right.yml
dex_retargeting/configs/offline/leap_hand_left.yml
dex_retargeting/configs/offline/leap_hand_right.yml
dex_retargeting/configs/offline/panda_gripper.yml
dex_retargeting/configs/offline/schunk_svh_hand_left.yml
dex_retargeting/configs/offline/schunk_svh_hand_right.yml
dex_retargeting/configs/offline/shadow_hand_left.yml
dex_retargeting/configs/offline/shadow_hand_right.yml
dex_retargeting/configs/teleop/ability_hand_left.yml
dex_retargeting/configs/teleop/ability_hand_left_dexpilot.yml
dex_retargeting/configs/teleop/ability_hand_right.yml
dex_retargeting/configs/teleop/ability_hand_right_dexpilot.yml
dex_retargeting/configs/teleop/allegro_hand_left.yml
dex_retargeting/configs/teleop/allegro_hand_left_dexpilot.yml
dex_retargeting/configs/teleop/allegro_hand_right.yml
dex_retargeting/configs/teleop/allegro_hand_right_dexpilot.yml
dex_retargeting/configs/teleop/inspire_hand_left.yml
dex_retargeting/configs/teleop/inspire_hand_left_dexpilot.yml
dex_retargeting/configs/teleop/inspire_hand_right.yml
dex_retargeting/configs/teleop/inspire_hand_right_dexpilot.yml
dex_retargeting/configs/teleop/leap_hand_left.yml
dex_retargeting/configs/teleop/leap_hand_left_dexpilot.yml
dex_retargeting/configs/teleop/leap_hand_right.yml
dex_retargeting/configs/teleop/leap_hand_right_dexpilot.yml
dex_retargeting/configs/teleop/panda_gripper.yml
dex_retargeting-0.5.0.dist-info/METADATA
dex_retargeting-0.5.0.dist-info/WHEEL
dex_retargeting-0.5.0.dist-info/licenses/LICENSE
dex_retargeting-0.5.0.dist-info/RECORD
