Metadata-Version: 2.4
Name: dex_retargeting
Version: 0.5.0
Summary: Hand pose retargeting for dexterous robot hand.
Project-URL: Homepage, https://github.com/dexsuite/dex-retargeting
Author-email: Yuzhe Qin <y1qin@ucsd.edu>
License: MIT
License-File: LICENSE
Classifier: Development Status :: 3 - Alpha
Classifier: Intended Audience :: Developers
Classifier: Intended Audience :: Science/Research
Classifier: License :: OSI Approved :: MIT License
Classifier: Natural Language :: English
Classifier: Programming Language :: Python :: 3
Classifier: Programming Language :: Python :: 3.7
Classifier: Programming Language :: Python :: 3.8
Classifier: Programming Language :: Python :: 3.9
Classifier: Programming Language :: Python :: 3.10
Classifier: Topic :: Scientific/Engineering :: Artificial Intelligence
Requires-Python: <3.13,>=3.7
Requires-Dist: anytree>=2.12.0
Requires-Dist: lxml>=5.2.2
Requires-Dist: nlopt>=2.8.0
Requires-Dist: numpy>=2.0.0
Requires-Dist: pin>=3.3.1
Requires-Dist: pytransform3d>=3.5.0
Requires-Dist: pyyaml>=6.0.0
Provides-Extra: dev
Requires-Dist: isort; extra == 'dev'
Requires-Dist: pytest; extra == 'dev'
Requires-Dist: ruff; extra == 'dev'
Provides-Extra: example
Requires-Dist: loguru; extra == 'example'
Requires-Dist: mediapipe; extra == 'example'
Requires-Dist: opencv-python; extra == 'example'
Requires-Dist: sapien==3.0.0b0; extra == 'example'
Requires-Dist: tqdm; extra == 'example'
Requires-Dist: tyro; extra == 'example'
